odeintw/__init__.py
odeintw/_odeintw.py
odeintw-1.0.2.dist-info/LICENSE
odeintw-1.0.2.dist-info/METADATA
odeintw-1.0.2.dist-info/WHEEL
odeintw-1.0.2.dist-info/top_level.txt
odeintw-1.0.2.dist-info/RECORD
