Metadata-Version: 2.1
Name: odeintw
Version: 1.0.2
Summary: Solve complex and matrix differential equations with scipy.integrate.odeint.
Home-page: https://github.com/WarrenWeckesser/odeintw
Author: Warren Weckesser
Keywords: scipy odeint
Classifier: Programming Language :: Python :: 2.7
Classifier: Programming Language :: Python :: 3
Classifier: License :: OSI Approved :: BSD License
Classifier: Operating System :: OS Independent
License-File: LICENSE
Requires-Dist: scipy
